[
  {
    "simp": "爱心",
    "trad": "愛心",
    "pinyin": "àixīn",
    "english": "compassion; loving heart"
  },
  {
    "simp": "安慰",
    "trad": "安慰",
    "pinyin": "ānwèi",
    "english": "to comfort; console"
  },
  {
    "simp": "安装",
    "trad": "安裝",
    "pinyin": "ānzhuāng",
    "english": "to install; to fix"
  },
  {
    "simp": "岸",
    "trad": "岸",
    "pinyin": "àn",
    "english": "bank; shore; coast"
  },
  {
    "simp": "暗",
    "trad": "暗",
    "pinyin": "àn",
    "english": "dark; gloomy"
  },
  {
    "simp": "熬夜",
    "trad": "熬夜",
    "pinyin": "áoyè",
    "english": "to stay up late"
  },
  {
    "simp": "把握",
    "trad": "把握",
    "pinyin": "bǎwò",
    "english": "to grasp; to hold; assurance"
  },
  {
    "simp": "摆",
    "trad": "擺",
    "pinyin": "bǎi",
    "english": "to arrange; to put; to swing"
  },
  {
    "simp": "办理",
    "trad": "辦理",
    "pinyin": "bànlǐ",
    "english": "to handle; to transact"
  },
  {
    "simp": "傍晚",
    "trad": "傍晚",
    "pinyin": "bàngwǎn",
    "english": "evening; dusk"
  }
]